{"chunk_definitions":[{"row":59,"row_count":1,"visible":true,"expansion_state":0,"options":{"engine":"r","include":false,"label":"unnamed-chunk-9","dev":"png"},"document_id":"0C16B7B3","chunk_id":"clph2uj9ow6pv","chunk_label":"unnamed-chunk-1"},{"row":73,"row_count":1,"visible":true,"expansion_state":0,"options":{"engine":"r","label":"unnamed-chunk-3","dev":"png"},"document_id":"0C16B7B3","chunk_id":"c5t07lytixxk6","chunk_label":"unnamed-chunk-2"},{"row":83,"row_count":1,"visible":true,"expansion_state":0,"options":{"engine":"r","label":"unnamed-chunk-4","dev":"png"},"document_id":"0C16B7B3","chunk_id":"c17kbsi6jsyof","chunk_label":"unnamed-chunk-3"},{"row":93,"row_count":1,"visible":true,"expansion_state":0,"options":{"engine":"r","label":"unnamed-chunk-5","dev":"png"},"document_id":"0C16B7B3","chunk_id":"c5t1hmhogx1bn","chunk_label":"unnamed-chunk-4"},{"row":124,"row_count":1,"visible":true,"expansion_state":0,"options":{"engine":"r","label":"unnamed-chunk-6","dev":"png"},"document_id":"0C16B7B3","chunk_id":"c6frtbk70j07t","chunk_label":"unnamed-chunk-5"},{"row":166,"row_count":1,"visible":true,"expansion_state":0,"options":{"engine":"r","label":"unnamed-chunk-7","dev":"png"},"document_id":"0C16B7B3","chunk_id":"cbo0ssaac7toc","chunk_label":"unnamed-chunk-6"},{"row":185,"row_count":1,"visible":true,"expansion_state":0,"options":{"engine":"r","message":false,"label":"unnamed-chunk-8","dev":"png"},"document_id":"0C16B7B3","chunk_id":"cth7bq2tl0vq8","chunk_label":"unnamed-chunk-7"}],"doc_write_time":1734518799}